sdflit/__init__.py
sdflit/__init__.pyi
sdflit/py.typed
sdflit/sdflit.cpython-311-darwin.so
sdflit-0.2.8.dist-info/METADATA
sdflit-0.2.8.dist-info/WHEEL
sdflit-0.2.8.dist-info/licenses/LICENSE
sdflit-0.2.8.dist-info/RECORD
