Metadata-Version: 2.4
Name: sdflit
Version: 0.2.8
Classifier: Programming Language :: Rust
Classifier: Programming Language :: Python :: Implementation :: CPython
Classifier: Programming Language :: Python :: Implementation :: PyPy
License-File: LICENSE
Summary: Fast and Robust Signed Distance Function Library
Keywords: sdf,pyo3
Author-email: yzx9 <pypi@yzx9.xyz>
License: Apache-2.0
Requires-Python: >=3.8
Project-URL: repository, https://github.com/yzx9/sdflit
